Mending/__init__.py
Overwrite/Core.py
Overwrite/__init__.py
Overwrite/main.py
Mending-0.1.2.dist-info/METADATA
Mending-0.1.2.dist-info/WHEEL
Mending-0.1.2.dist-info/top_level.txt
Mending-0.1.2.dist-info/RECORD
