Metadata-Version: 2.1
Name: Mending
Version: 0.1.2
Summary: UNKNOWN
Home-page: https://github.com/Beyonder-Zack/Mending
Author: Zack the White, Qcmcmc
Author-email: ssongaj@connect.ust.hk
License: MIT
Platform: UNKNOWN
Classifier: Development Status :: 3 - Alpha
Classifier: Programming Language :: Python :: 3
